tests/__init__.py
tests/test_client.py
tests/test_exceptions.py
tests/test_models.py
vbaas/__init__.py
vbaas/client.py
vbaas/exceptions.py
vbaas/models.py
vbaas_python_sdk-1.0.3.dist-info/licenses/LICENSE
vbaas_python_sdk-1.0.3.dist-info/METADATA
vbaas_python_sdk-1.0.3.dist-info/WHEEL
vbaas_python_sdk-1.0.3.dist-info/top_level.txt
vbaas_python_sdk-1.0.3.dist-info/RECORD
