Metadata-Version: 2.4
Name: vbaas-python-sdk
Version: 1.0.3
Summary: Python SDK for VFD Bank as a Service (VBaaS) API
Home-page: https://github.com/GiddyNaya/vfd-vbaas
Author: VBaaS SDK
Author-email: VBaaS SDK <ogbonnagideon5@gmail.com>
License: MIT
Project-URL: Homepage, https://github.com/GiddyNaya/vfd-vbaas
Project-URL: Documentation, https://vbaas-docs.vfdtech.ng/
Project-URL: Repository, https://github.com/GiddyNaya/vfd-vbaas.git
Project-URL: Bug Tracker, https://github.com/GiddyNaya/vfd-vbaas/issues
Classifier: Development Status :: 4 - Beta
Classifier: Intended Audience :: Developers
Classifier: License :: OSI Approved :: MIT License
Classifier: Operating System :: OS Independent
Classifier: Programming Language :: Python :: 3.9
Classifier: Programming Language :: Python :: 3.10
Classifier: Programming Language :: Python :: 3.11
Requires-Python: >=3.9
License-File: LICENSE
Requires-Dist: requests>=2.25.0
Requires-Dist: typing-extensions>=4.0.0
Provides-Extra: dev
Requires-Dist: pytest>=6.0; extra == "dev"
Requires-Dist: pytest-cov>=2.0; extra == "dev"
Requires-Dist: pytest-mock>=3.0; extra == "dev"
Requires-Dist: black>=21.0; extra == "dev"
Requires-Dist: flake8>=3.8; extra == "dev"
Requires-Dist: mypy>=0.910; extra == "dev"
Requires-Dist: isort>=5.0; extra == "dev"
Requires-Dist: types-requests>=2.25.0; extra == "dev"
Dynamic: author
Dynamic: home-page
Dynamic: license-file
Dynamic: requires-python
